Workbook

Sheet Memo
A1: M/S Swarna Enterprise
A2: Bill of: Sales Central-Cookware
A5: Invoice No: | B5: 24865 | D5: Party Code:
D6: Party Name: | E6: Digital Aluminium
A7: Ref No: | B7: D4-05092/26 | D7: Address: | E7: Safa, Mathbaria
A8: Date: | B8: 46216 | D8: Contact: | E8: 1714510583
A9: Gate Pass Ref: | B9: 45863 | D9: NID:
A11: Note: | B11: D4-05092/26 .Van-Shamim
A13: Serial No | B13: Description Of Goods | C13: Quantity | D13: Rate | E13: Amount
A14: 1 | B14: Infrared Cooker CMT-22 | C14: 1 | D14: 3375 | E14: =IF(OR(C14="", D14=""), "", C14*D14) -> 3375
E15: =IF(OR(C15="", D15=""), "", C15*D15)
E16: =IF(OR(C16="", D16=""), "", C16*D16)
E17: =IF(OR(C17="", D17=""), "", C17*D17)
E18: =IF(OR(C18="", D18=""), "", C18*D18)
E19: =IF(OR(C19="", D19=""), "", C19*D19)
A20: 2 | B20: SS Electric Kettle-1.8Ltr (UnDelivery) | C20: 1 | D20: 0 | E20: =IF(OR(C20="", D20=""), "", C20*D20) -> 0
A21: 3 | B21: SS Electric Kettle- Lower Part Black | C21: 1 | D21: 0 | E21: =IF(OR(C21="", D21=""), "", C21*D21) -> 0
E22: =IF(OR(C22="", D22=""), "", C22*D22)
E23: =IF(OR(C23="", D23=""), "", C23*D23)
E24: =IF(OR(C24="", D24=""), "", C24*D24)
E25: =IF(OR(C25="", D25=""), "", C25*D25)
E26: =IF(OR(C26="", D26=""), "", C26*D26)
E27: =IF(OR(C27="", D27=""), "", C27*D27)
E28: =IF(OR(C28="", D28=""), "", C28*D28)
E29: =IF(OR(C29="", D29=""), "", C29*D29)
E30: =IF(OR(C30="", D30=""), "", C30*D30)
E31: =IF(OR(C31="", D31=""), "", C31*D31)
E32: =IF(OR(C32="", D32=""), "", C32*D32)
E33: =IF(OR(C33="", D33=""), "", C33*D33)
... E35: =IF(OR(C35="", D35=""), "", C35*D35)
A36: TOTAL: | B36: =SUM(C14:C35) -> 3 | E36: =SUM(E14:E35) -> 3375
A37: Cash Discount | B37: (-)% | E37: =E36*(D37/E36) -> 0
A38: Commission | B38: (-)% | E38: =(E36-E37)*(D38/100) -> 0
A39: Commission | B39: (-)% | E39: =(E36-E37-E38)*(D39/100) -> 0
A40: Final Total: | B40: =E36-E37-E38-E39 -> 3375
A44: Prepared By:....... | B44: Checked BY:........ | D44: Authorized BY:....... | E44: Customer Signature:.....

Sheet Sheet2
D4: Input | F4: K/Y
D8: Group | E8: Code | F8: Name | G8: Size | H8: DP | I8: D. 12
D9: {=_xlfn._xlws.FILTER(Sheet1!B2:F512, TRIM(Sheet1!B2:B512) = TRIM(F4))} -> K/Y | E9: HE18-08 | F9: Glass Electric Kettle | G9: 1.8 | H9: 1300 | I9: {=IFERROR(IF(E9="", "", INDEX(Sheet1!$G:$J, MATCH(E9, Sheet1!$C:$C, 0), IF(COUNTIF(Sheet1!$G:$G, $I$8)>0, 1, IF(COUNTIF(Sheet1!$H:$H, $I$8)>0, 2, IF(COUNTIF(Sheet1!$I:$I, $I$8)>0, 3, IF(COUNTIF(Sheet1!$J:$J, $I$8)>0, 4, 0)))))), "")} -> 1144
D10: K/Y | E10: HS18-07 | F10: PL Electric Kettle | G10: 1.8 | H10: 950 | I10: {=IFERROR(IF(E10="", "", INDEX(Sheet1!$G:$J, MATCH(E10, Sheet1!$C:$C, 0), IF(COUNTIF(Sheet1!$G:$G, $I$8)>0, 1, IF(COUNTIF(Sheet1!$H:$H, $I$8)>0, 2, IF(COUNTIF(Sheet1!$I:$I, $I$8)>0, 3, IF(COUNTIF(Sheet1!$J:$J, $I$8)>0, 4, 0)))))), "")} -> 836
D11: K/Y | E11: HS18-05 | F11: SS Electric Kettle | G11: 1.8 | H11: 835 | I11: {=IFERROR(IF(E11="", "", INDEX(Sheet1!$G:$J, MATCH(E11, Sheet1!$C:$C, 0), IF(COUNTIF(Sheet1!$G:$G, $I$8)>0, 1, IF(COUNTIF(Sheet1!$H:$H, $I$8)>0, 2, IF(COUNTIF(Sheet1!$I:$I, $I$8)>0, 3, IF(COUNTIF(Sheet1!$J:$J, $I$8)>0, 4, 0)))))), "")} -> 734.8
D12: K/Y | E12: HS18-06 | F12: SS Electric Kettle | G12: 2.2 | H12: 950 | I12: {=IFERROR(IF(E12="", "", INDEX(Sheet1!$G:$J, MATCH(E12, Sheet1!$C:$C, 0), IF(COUNTIF(Sheet1!$G:$G, $I$8)>0, 1, IF(COUNTIF(Sheet1!$H:$H, $I$8)>0, 2, IF(COUNTIF(Sheet1!$I:$I, $I$8)>0, 3, IF(COUNTIF(Sheet1!$J:$J, $I$8)>0, 4, 0)))))), "")} -> 836
I13: {=IFERROR(IF(E13="", "", INDEX(Sheet1!$G:$J, MATCH(E13, Sheet1!$C:$C, 0), IF(COUNTIF(Sheet1!$G:$G, $I$8)>0, 1, IF(COUNTIF(Sheet1!$H:$H, $I$8)>0, 2, IF(COUNTIF(Sheet1!$I:$I, $I$8)>0, 3, IF(COUNTIF(Sheet1!$J:$J, $I$8)>0, 4, 0)))))), "")}
I14: {=IFERROR(IF(E14="", "", INDEX(Sheet1!$G:$J, MATCH(E14, Sheet1!$C:$C, 0), IF(COUNTIF(Sheet1!$G:$G, $I$8)>0, 1, IF(COUNTIF(Sheet1!$H:$H, $I$8)>0, 2, IF(COUNTIF(Sheet1!$I:$I, $I$8)>0, 3, IF(COUNTIF(Sheet1!$J:$J, $I$8)>0, 4, 0)))))), "")}
I15: {=IFERROR(IF(E15="", "", INDEX(Sheet1!$G:$J, MATCH(E15, Sheet1!$C:$C, 0), IF(COUNTIF(Sheet1!$G:$G, $I$8)>0, 1, IF(COUNTIF(Sheet1!$H:$H, $I$8)>0, 2, IF(COUNTIF(Sheet1!$I:$I, $I$8)>0, 3, IF(COUNTIF(Sheet1!$J:$J, $I$8)>0, 4, 0)))))), "")}
I16: {=IFERROR(IF(E16="", "", INDEX(Sheet1!$G:$J, MATCH(E16, Sheet1!$C:$C, 0), IF(COUNTIF(Sheet1!$G:$G, $I$8)>0, 1, IF(COUNTIF(Sheet1!$H:$H, $I$8)>0, 2, IF(COUNTIF(Sheet1!$I:$I, $I$8)>0, 3, IF(COUNTIF(Sheet1!$J:$J, $I$8)>0, 4, 0)))))), "")}
I17: {=IFERROR(IF(E17="", "", INDEX(Sheet1!$G:$J, MATCH(E17, Sheet1!$C:$C, 0), IF(COUNTIF(Sheet1!$G:$G, $I$8)>0, 1, IF(COUNTIF(Sheet1!$H:$H, $I$8)>0, 2, IF(COUNTIF(Sheet1!$I:$I, $I$8)>0, 3, IF(COUNTIF(Sheet1!$J:$J, $I$8)>0, 4, 0)))))), "")}
I18: {=IFERROR(IF(E18="", "", INDEX(Sheet1!$G:$J, MATCH(E18, Sheet1!$C:$C, 0), IF(COUNTIF(Sheet1!$G:$G, $I$8)>0, 1, IF(COUNTIF(Sheet1!$H:$H, $I$8)>0, 2, IF(COUNTIF(Sheet1!$I:$I, $I$8)>0, 3, IF(COUNTIF(Sheet1!$J:$J, $I$8)>0, 4, 0)))))), "")}
I19: {=IFERROR(IF(E19="", "", INDEX(Sheet1!$G:$J, MATCH(E19, Sheet1!$C:$C, 0), IF(COUNTIF(Sheet1!$G:$G, $I$8)>0, 1, IF(COUNTIF(Sheet1!$H:$H, $I$8)>0, 2, IF(COUNTIF(Sheet1!$I:$I, $I$8)>0, 3, IF(COUNTIF(Sheet1!$J:$J, $I$8)>0, 4, 0)))))), "")}
I20: {=IFERROR(IF(E20="", "", INDEX(Sheet1!$G:$J, MATCH(E20, Sheet1!$C:$C, 0), IF(COUNTIF(Sheet1!$G:$G, $I$8)>0, 1, IF(COUNTIF(Sheet1!$H:$H, $I$8)>0, 2, IF(COUNTIF(Sheet1!$I:$I, $I$8)>0, 3, IF(COUNTIF(Sheet1!$J:$J, $I$8)>0, 4, 0)))))), "")}
I21: {=IFERROR(IF(E21="", "", INDEX(Sheet1!$G:$J, MATCH(E21, Sheet1!$C:$C, 0), IF(COUNTIF(Sheet1!$G:$G, $I$8)>0, 1, IF(COUNTIF(Sheet1!$H:$H, $I$8)>0, 2, IF(COUNTIF(Sheet1!$I:$I, $I$8)>0, 3, IF(COUNTIF(Sheet1!$J:$J, $I$8)>0, 4, 0)))))), "")}
I22: {=IFERROR(IF(E22="", "", INDEX(Sheet1!$G:$J, MATCH(E22, Sheet1!$C:$C, 0), IF(COUNTIF(Sheet1!$G:$G, $I$8)>0, 1, IF(COUNTIF(Sheet1!$H:$H, $I$8)>0, 2, IF(COUNTIF(Sheet1!$I:$I, $I$8)>0, 3, IF(COUNTIF(Sheet1!$J:$J, $I$8)>0, 4, 0)))))), "")}
I23: {=IFERROR(IF(E23="", "", INDEX(Sheet1!$G:$J, MATCH(E23, Sheet1!$C:$C, 0), IF(COUNTIF(Sheet1!$G:$G, $I$8)>0, 1, IF(COUNTIF(Sheet1!$H:$H, $I$8)>0, 2, IF(COUNTIF(Sheet1!$I:$I, $I$8)>0, 3, IF(COUNTIF(Sheet1!$J:$J, $I$8)>0, 4, 0)))))), "")}
I24: {=IFERROR(IF(E24="", "", INDEX(Sheet1!$G:$J, MATCH(E24, Sheet1!$C:$C, 0), IF(COUNTIF(Sheet1!$G:$G, $I$8)>0, 1, IF(COUNTIF(Sheet1!$H:$H, $I$8)>0, 2, IF(COUNTIF(Sheet1!$I:$I, $I$8)>0, 3, IF(COUNTIF(Sheet1!$J:$J, $I$8)>0, 4, 0)))))), "")}
... I774: {=IFERROR(IF(E774="", "", INDEX(Sheet1!$G:$J, MATCH(E774, Sheet1!$C:$C, 0), IF(COUNTIF(Sheet1!$G:$G, $I$8)>0, 1, IF(COUNTIF(Sheet1!$H:$H, $I$8)>0, 2, IF(COUNTIF(Sheet1!$I:$I, $I$8)>0, 3, IF(COUNTIF(Sheet1!$J:$J, $I$8)>0, 4, 0)))))), "")}

Sheet Sheet1
A1: SL | B1: Group | C1: Code | D1: Rice Cooker | E1: Size | F1: DP | G1: D. 10 | H1: B. 12 | I1: D. 12 | J1: B. 14
A2: 1 | B2: R/C | C2: HA15-01 | D2: Still R/C- SS+Alu Pot | E2: 1.8 | F2: 2425 | G2: =F2*90% -> 2182.5 | H2: =F2*90%*98% -> 2138.85 | I2: =F2*88% -> 2134 | J2: =F2*88%*98% -> 2091.32
A3: 2 | B3: R/C | C3: HA15-02 | D3: Still R/C- Singel Alu Pot | E3: 1.8 | F3: 2075 | G3: =F3*90% -> 1867.5 | H3: =F3*90%*98% -> 1830.15 | I3: =F3*88% -> 1826 | J3: =F3*88%*98% -> 1789.48
A4: 3 | B4: R/C | C4: HA15-03 | D4: Still R/C- Singel SS Pot | E4: 1.8 | F4: 2075 | G4: =F4*90% -> 1867.5 | H4: =F4*90%*98% -> 1830.15 | I4: =F4*88% -> 1826 | J4: =F4*88%*98% -> 1789.48
A5: 4 | B5: R/C | C5: HA15-04 | D5: Double SS Pot | E5: 1.8 | F5: 2535 | G5: =F5*90% -> 2281.5 | H5: =F5*90%*98% -> 2235.87 | I5: =F5*88% -> 2230.8 | J5: =F5*88%*98% -> 2186.184
A6: 5 | B6: R/C | C6: HA15-05 | D6: F.B Double SS Pot | E6: 1.8 | F6: 2585 | G6: =F6*90% -> 2326.5 | H6: =F6*90%*98% -> 2279.97 | I6: =F6*88% -> 2274.8 | J6: =F6*88%*98% -> 2229.304
A7: 6 | B7: R/C | C7: HA15-07 | D7: F.B R/C- SS+Alu Pot | E7: 1.8 | F7: 2475 | G7: =F7*90% -> 2227.5 | H7: =F7*90%*98% -> 2182.95 | I7: =F7*88% -> 2178 | J7: =F7*88%*98% -> 2134.44
A8: 7 | B8: R/C | C8: HA15-08 | D8: F.B R/C- Singel Alu Pot | E8: 1.8 | F8: 2125 | G8: =F8*90% -> 1912.5 | H8: =F8*90%*98% -> 1874.25 | I8: =F8*88% -> 1870 | J8: =F8*88%*98% -> 1832.6
A9: 8 | B9: R/C | C9: HA15-10 | D9: F.B R/C- Singel SS Pot | E9: 1.8 | F9: 2125 | G9: =F9*90% -> 1912.5 | H9: =F9*90%*98% -> 1874.25 | I9: =F9*88% -> 1870 | J9: =F9*88%*98% -> 1832.6
A10: 9 | B10: R/C | C10: HA15-11 | D10: Still R/C- SS+Alu Pot | E10: 2.8 | F10: 2965 | G10: =F10*90% -> 2668.5 | H10: =F10*90%*98% -> 2615.13 | I10: =F10*88% -> 2609.2 | J10: =F10*88%*98% -> 2557.016
A11: 10 | B11: R/C | C11: HA15-12 | D11: Still R/C- Singel Alu Pot | E11: 2.8 | F11: 2570 | G11: =F11*90% -> 2313 | H11: =F11*90%*98% -> 2266.74 | I11: =F11*88% -> 2261.6 | J11: =F11*88%*98% -> 2216.368
A12: 11 | B12: R/C | C12: HA15-13 | D12: Still R/C- Singel SS Pot | E12: 2.8 | F12: 2570 | G12: =F12*90% -> 2313 | H12: =F12*90%*98% -> 2266.74 | I12: =F12*88% -> 2261.6 | J12: =F12*88%*98% -> 2216.368
A13: 12 | B13: R/C | C13: HA15-15 | D13: Double SS Pot | E13: 2.8 | F13: 3120 | G13: =F13*90% -> 2808 | H13: =F13*90%*98% -> 2751.84 | I13: =F13*88% -> 2745.6 | J13: =F13*88%*98% -> 2690.688
... A18: 17 | B18: R/C | C18: HR14-11 | D18: J.B R/C- SS+Alu Pot MC R+G Line | E18: 2.8 | F18: 3020 | G18: =F18*90% -> 2718 | H18: =F18*90%*98% -> 2663.64 | I18: =F18*88% -> 2657.6 | J18: =F18*88%*98% -> 2604.448
A21: SL | B21: Group | C21: Code | D21: Pressure Cooker | E21: Size | F21: DP | G21: D. 10 | H21: B. 12 | I21: D. 12 | J21: B. 14
A22: 1 | B22: P/C | C22: HA5-01 | D22: Pressure Cooker Straight | E22: 3.5 | F22: 1255 | G22: =F22*90% -> 1129.5 | H22: =F22*90%*98% -> 1106.91 | I22: =F22*88% -> 1104.4 | J22: =F22*88%*98% -> 1082.312
A23: 2 | B23: P/C | C23: HA5-02 | D23: Pressure Cooker Straight | E23: 4.5 | F23: 1530 | G23: =F23*90% -> 1377 | H23: =F23*90%*98% -> 1349.46 | I23: =F23*88% -> 1346.4 | J23: =F23*88%*98% -> 1319.472
A24: 3 | B24: P/C | C24: HA5-03 | D24: Pressure Cooker Straight | E24: 5.5 | F24: 1605 | G24: =F24*90% -> 1444.5 | H24: =F24*90%*98% -> 1415.61 | I24: =F24*88% -> 1412.4 | J24: =F24*88%*98% -> 1384.152
A25: 4 | B25: P/C | C25: HA5-04 | D25: Pressure Cooker Straight | E25: 6.5 | F25: 1730 | G25: =F25*90% -> 1557 | H25: =F25*90%*98% -> 1525.86 | I25: =F25*88% -> 1522.4 | J25: =F25*88%*98% -> 1491.952
A26: 5 | B26: P/C | C26: HA5-11 | D26: Pressure Cooker Straight | E26: 8 | F26: 2480 | G26: =F26*90% -> 2232 | H26: =F26*90%*98% -> 2187.36 | I26: =F26*88% -> 2182.4 | J26: =F26*88%*98% -> 2138.752
A27: 6 | B27: P/C | C27: HA5-05 | D27: Pressure Cooker Straight IB | E27: 3.5 | F27: 1330 | G27: =F27*90% -> 1197 | H27: =F27*90%*98% -> 1173.06 | I27: =F27*88% -> 1170.4 | J27: =F27*88%*98% -> 1146.992
A28: 7 | B28: P/C | C28: HA5-06 | D28: Pressure Cooker Straight IB | E28: 4.5 | F28: 1605 | G28: =F28*90% -> 1444.5 | H28: =F28*90%*98% -> 1415.61 | I28: =F28*88% -> 1412.4 | J28: =F28*88%*98% -> 1384.152
A29: 8 | B29: P/C | C29: HA5-07 | D29: Pressure Cooker Straight IB | E29: 5.5 | F29: 1680 | G29: =F29*90% -> 1512 | H29: =F29*90%*98% -> 1481.76 | I29: =F29*88% -> 1478.4 | J29: =F29*88%*98% -> 1448.832
A30: 9 | B30: P/C | C30: HA5-08 | D30: Pressure Cooker Straight IB | E30: 6.5 | F30: 1805 | G30: =F30*90% -> 1624.5 | H30: =F30*90%*98% -> 1592.01 | I30: =F30*88% -> 1588.4 | J30: =F30*88%*98% -> 1556.632
A31: 10 | B31: P/C | C31: HA5-12 | D31: Pressure Cooker Straight IB | E31: 8 | F31: 2555 | G31: =F31*90% -> 2299.5 | H31: =F31*90%*98% -> 2253.51 | I31: =F31*88% -> 2248.4 | J31: =F31*88%*98% -> 2203.432
A32: 11 | B32: P/C | C32: HA5-09 | D32: Pressure Cooker Straight | E32: 2.5 | F32: 1155 | G32: =F32*90% -> 1039.5 | H32: =F32*90%*98% -> 1018.71 | I32: =F32*88% -> 1016.4 | J32: =F32*88%*98% -> 996.072
A33: 12 | B33: P/C | C33: HA5-10 | D33: Pressure Cooker Straight IB | E33: 2.5 | F33: 1230 | G33: =F33*90% -> 1107 | H33: =F33*90%*98% -> 1084.86 | I33: =F33*88% -> 1082.4 | J33: =F33*88%*98% -> 1060.752
... A39: 18 | B39: P/C | C39: HA6-06 | D39: Pressure Cooker Oval IB | E39: 5.5 | F39: 1760 | G39: =F39*90% -> 1584 | H39: =F39*90%*98% -> 1552.32 | I39: =F39*88% -> 1548.8 | J39: =F39*88%*98% -> 1517.824
A40: 19 | B40: P/C | C40: HS21-01 | D40: SS 3 Layer Pressure Cooker | E40: 3.5 | F40: 1840 | G40: =F40*94% -> 1729.6 | H40: =F40*94%*98% -> 1695.008
A41: 20 | B41: P/C | C41: HS21-02 | D41: SS 3 Layer Pressure Cooker | E41: 4.5 | F41: 2050 | G41: =F41*94% -> 1927 | H41: =F41*94%*98% -> 1888.46
A42: 21 | B42: P/C | C42: HS21-03 | D42: SS 3 Layer Pressure Cooker | E42: 5.5 | F42: 2365 | G42: =F42*94% -> 2223.1 | H42: =F42*94%*98% -> 2178.638
A43: 22 | B43: P/C | C43: HS21-04 | D43: SS 3 Layer Pressure Cooker | E43: 6.5 | F43: 2575 | G43: =F43*94% -> 2420.5 | H43: =F43*94%*98% -> 2372.09
A48: SL | B48: Group | C48: Code | D48: Casserole | E48: Size | F48: DP | G48: D. 10 | H48: B. 12 | I48: D. 12 | J48: B. 14
A49: 1 | B49: C/P | C49: HAF1-01 | D49: Casserole Pan | E49: 18 | F49: 975 | G49: =F49*90% -> 877.5 | H49: =F49*90%*98% -> 859.95 | I49: =F49*88% -> 858 | J49: =F49*88%*98% -> 840.84
A50: 2 | B50: C/P | C50: HAF1-02 | D50: Casserole Pan | E50: 20 | F50: 1105 | G50: =F50*90% -> 994.5 | H50: =F50*90%*98% -> 974.61 | I50: =F50*88% -> 972.4 | J50: =F50*88%*98% -> 952.952
A51: 3 | B51: C/P | C51: HAF1-03 | D51: Casserole Pan | E51: 22 | F51: 1240 | G51: =F51*90% -> 1116 | H51: =F51*90%*98% -> 1093.68 | I51: =F51*88% -> 1091.2 | J51: =F51*88%*98% -> 1069.376
A52: 4 | B52: C/P | C52: HAF1-04 | D52: Casserole Pan | E52: 24 | F52: 1435 | G52: =F52*90% -> 1291.5 | H52: =F52*90%*98% -> 1265.67 | I52: =F52*88% -> 1262.8 | J52: =F52*88%*98% -> 1237.544
A53: 5 | B53: C/P | C53: HAF1-05 | D53: Casserole Pan | E53: 26 | F53: 1570 | G53: =F53*90% -> 1413 | H53: =F53*90%*98% -> 1384.74 | I53: =F53*88% -> 1381.6 | J53: =F53*88%*98% -> 1353.968
A54: 6 | B54: C/P | C54: HAF1-06 | D54: Casserole Pan | E54: 28 | F54: 1820 | G54: =F54*90% -> 1638 | H54: =F54*90%*98% -> 1605.24 | I54: =F54*88% -> 1601.6 | J54: =F54*88%*98% -> 1569.568
A55: 7 | B55: C/P | C55: HAF1-07 | D55: Casserole Pan IB | E55: 18 | F55: 1050 | G55: =F55*90% -> 945 | H55: =F55*90%*98% -> 926.1 | I55: =F55*88% -> 924 | J55: =F55*88%*98% -> 905.52
A56: 8 | B56: C/P | C56: HAF1-08 | D56: Casserole Pan IB | E56: 20 | F56: 1190 | G56: =F56*90% -> 1071 | H56: =F56*90%*98% -> 1049.58 | I56: =F56*88% -> 1047.2 | J56: =F56*88%*98% -> 1026.256
A57: 9 | B57: C/P | C57: HAF1-09 | D57: Casserole Pan IB | E57: 22 | F57: 1320 | G57: =F57*90% -> 1188 | H57: =F57*90%*98% -> 1164.24 | I57: =F57*88% -> 1161.6 | J57: =F57*88%*98% -> 1138.368
A58: 10 | B58: C/P | C58: HAF1-10 | D58: Casserole Pan IB | E58: 24 | F58: 1510 | G58: =F58*90% -> 1359 | H58: =F58*90%*98% -> 1331.82 | I58: =F58*88% -> 1328.8 | J58: =F58*88%*98% -> 1302.224
A59: 11 | B59: C/P | C59: HAF1-11 | D59: Casserole Pan IB | E59: 26 | F59: 1640 | G59: =F59*90% -> 1476 | H59: =F59*90%*98% -> 1446.48 | I59: =F59*88% -> 1443.2 | J59: =F59*88%*98% -> 1414.336
A60: 12 | B60: C/P | C60: HAF1-12 | D60: Casserole Pan IB | E60: 28 | F60: 1900 | G60: =F60*90% -> 1710 | H60: =F60*90%*98% -> 1675.8 | I60: =F60*88% -> 1672 | J60: =F60*88%*98% -> 1638.56
A63: SL | B63: Group | C63: Code | D63: Deep Frypan | E63: Size | F63: DP | G63: D. 10 | H63: B. 12 | I63: D. 12 | J63: B. 14
A64: 1 | B64: F/P | C64: HAF2-01 | D64: Deep Frypan | E64: 22 | F64: 1145 | G64: =F64*90% -> 1030.5 | H64: =F64*90%*98% -> 1009.89 | I64: =F64*88% -> 1007.6 | J64: =F64*88%*98% -> 987.448
A65: 2 | B65: F/P | C65: HAF2-02 | D65: Deep Frypan | E65: 24 | F65: 1315 | G65: =F65*90% -> 1183.5 | H65: =F65*90%*98% -> 1159.83 | I65: =F65*88% -> 1157.2 | J65: =F65*88%*98% -> 1134.056
A66: 3 | B66: F/P | C66: HAF2-03 | D66: Deep Frypan | E66: 26 | F66: 1405 | G66: =F66*90% -> 1264.5 | H66: =F66*90%*98% -> 1239.21 | I66: =F66*88% -> 1236.4 | J66: =F66*88%*98% -> 1211.672
A67: 4 | B67: F/P | C67: HAF2-04 | D67: Deep Frypan IB | E67: 22 | F67: 1220 | G67: =F67*90% -> 1098 | H67: =F67*90%*98% -> 1076.04 | I67: =F67*88% -> 1073.6 | J67: =F67*88%*98% -> 1052.128
A68: 5 | B68: F/P | C68: HAF2-05 | D68: Deep Frypan IB | E68: 24 | F68: 1405 | G68: =F68*90% -> 1264.5 | H68: =F68*90%*98% -> 1239.21 | I68: =F68*88% -> 1236.4 | J68: =F68*88%*98% -> 1211.672
A69: 6 | B69: F/P | C69: HAF2-06 | D69: Deep Frypan IB | E69: 26 | F69: 1505 | G69: =F69*90% -> 1354.5 | H69: =F69*90%*98% -> 1327.41 | I69: =F69*88% -> 1324.4 | J69: =F69*88%*98% -> 1297.912
A72: SL | B72: Group | C72: Code | D72: Frypan | E72: Size | F72: DP | G72: D. 10 | H72: B. 12 | I72: D. 12 | J72: B. 14
A73: 1 | B73: F/P | C73: HAF3-01 | D73: Frypan | E73: 20 | F73: 855 | G73: =F73*90% -> 769.5 | H73: =F73*90%*98% -> 754.11 | I73: =F73*88% -> 752.4 | J73: =F73*88%*98% -> 737.352
A74: 2 | B74: F/P | C74: HAF3-02 | D74: Frypan | E74: 22 | F74: 980 | G74: =F74*90% -> 882 | H74: =F74*90%*98% -> 864.36 | I74: =F74*88% -> 862.4 | J74: =F74*88%*98% -> 845.152
A75: 3 | B75: F/P | C75: HAF3-03 | D75: Frypan | E75: 24 | F75: 1080 | G75: =F75*90% -> 972 | H75: =F75*90%*98% -> 952.56 | I75: =F75*88% -> 950.4 | J75: =F75*88%*98% -> 931.392
A76: 4 | B76: F/P | C76: HAF3-04 | D76: Frypan | E76: 26 | F76: 1155 | G76: =F76*90% -> 1039.5 | H76: =F76*90%*98% -> 1018.71 | I76: =F76*88% -> 1016.4 | J76: =F76*88%*98% -> 996.072
A77: 5 | B77: F/P | C77: HAF3-05 | D77: Frypan | E77: 28 | F77: 1285 | G77: =F77*90% -> 1156.5 | H77: =F77*90%*98% -> 1133.37 | I77: =F77*88% -> 1130.8 | J77: =F77*88%*98% -> 1108.184
A78: 6 | B78: F/P | C78: HAF3-06 | D78: Frypan IB | E78: 20 | F78: 920 | G78: =F78*90% -> 828 | H78: =F78*90%*98% -> 811.44 | I78: =F78*88% -> 809.6 | J78: =F78*88%*98% -> 793.408
A79: 7 | B79: F/P | C79: HAF3-07 | D79: Frypan IB | E79: 22 | F79: 1040 | G79: =F79*90% -> 936 | H79: =F79*90%*98% -> 917.28 | I79: =F79*88% -> 915.2 | J79: =F79*88%*98% -> 896.896
A80: 8 | B80: F/P | C80: HAF3-08 | D80: Frypan IB | E80: 24 | F80: 1155 | G80: =F80*90% -> 1039.5 | H80: =F80*90%*98% -> 1018.71 | I80: =F80*88% -> 1016.4 | J80: =F80*88%*98% -> 996.072
A81: 9 | B81: F/P | C81: HAF3-09 | D81: Frypan IB | E81: 26 | F81: 1240 | G81: =F81*90% -> 1116 | H81: =F81*90%*98% -> 1093.68 | I81: =F81*88% -> 1091.2 | J81: =F81*88%*98% -> 1069.376
A82: 10 | B82: F/P | C82: HAF3-10 | D82: Frypan IB | E82: 28 | F82: 1375 | G82: =F82*90% -> 1237.5 | H82: =F82*90%*98% -> 1212.75 | I82: =F82*88% -> 1210 | J82: =F82*88%*98% -> 1185.8
A83: 1 | B83: F/P | C83: HAF3-21 | D83: Frypan Without Lid | E83: 20 | F83: 665 | G83: =F83*90% -> 598.5 | H83: =F83*90%*98% -> 586.53 | I83: =F83*88% -> 585.2 | J83: =F83*88%*98% -> 573.496
A84: 2 | B84: F/P | C84: HAF3-22 | D84: Frypan Without Lid | E84: 22 | F84: 785 | G84: =F84*90% -> 706.5 | H84: =F84*90%*98% -> 692.37 | I84: =F84*88% -> 690.8 | J84: =F84*88%*98% -> 676.984
... A92: 10 | B92: F/P | C92: HAF3-30 | D92: Frypan Without Lid IB | E92: 28 | F92: 1170 | G92: =F92*90% -> 1053 | H92: =F92*90%*98% -> 1031.94 | I92: =F92*88% -> 1029.6 | J92: =F92*88%*98% -> 1009.008
A95: SL | B95: Group | C95: Code | D95: Wokpan | E95: Size | F95: DP | G95: D. 10 | H95: B. 12 | I95: D. 12 | J95: B. 14
A96: 1 | B96: W/P | C96: HA12-01 | D96: Wokpan With Glass Lid | E96: 20 | F96: 995 | G96: =F96*90% -> 895.5 | H96: =F96*90%*98% -> 877.59 | I96: =F96*88% -> 875.6 | J96: =F96*88%*98% -> 858.088
A97: 2 | B97: W/P | C97: HA12-02 | D97: Wokpan With Glass Lid | E97: 22 | F97: 1125 | G97: =F97*90% -> 1012.5 | H97: =F97*90%*98% -> 992.25 | I97: =F97*88% -> 990 | J97: =F97*88%*98% -> 970.2
A98: 3 | B98: W/P | C98: HA12-03 | D98: Wokpan With Glass Lid | E98: 24 | F98: 1205 | G98: =F98*90% -> 1084.5 | H98: =F98*90%*98% -> 1062.81 | I98: =F98*88% -> 1060.4 | J98: =F98*88%*98% -> 1039.192
A99: 4 | B99: W/P | C99: HA12-04 | D99: Wokpan With Glass Lid | E99: 26 | F99: 1360 | G99: =F99*90% -> 1224 | H99: =F99*90%*98% -> 1199.52 | I99: =F99*88% -> 1196.8 | J99: =F99*88%*98% -> 1172.864
A100: 5 | B100: W/P | C100: HA12-05 | D100: Wokpan With Glass Lid | E100: 28 | F100: 1500 | G100: =F100*90% -> 1350 | H100: =F100*90%*98% -> 1323 | I100: =F100*88% -> 1320 | J100: =F100*88%*98% -> 1293.6
A101: 6 | B101: W/P | C101: HA12-06 | D101: Wokpan With Glass Lid | E101: 30 | F101: 1630 | G101: =F101*90% -> 1467 | H101: =F101*90%*98% -> 1437.66 | I101: =F101*88% -> 1434.4 | J101: =F101*88%*98% -> 1405.712
A102: 7 | B102: W/P | C102: HA12-07 | D102: Wokpan With Glass Lid IB | E102: 20 | F102: 1080 | G102: =F102*90% -> 972 | H102: =F102*90%*98% -> 952.56 | I102: =F102*88% -> 950.4 | J102: =F102*88%*98% -> 931.392
A103: 8 | B103: W/P | C103: HA12-08 | D103: Wokpan With Glass Lid IB | E103: 22 | F103: 1205 | G103: =F103*90% -> 1084.5 | H103: =F103*90%*98% -> 1062.81 | I103: =F103*88% -> 1060.4 | J103: =F103*88%*98% -> 1039.192
A104: 9 | B104: W/P | C104: HA12-09 | D104: Wokpan With Glass Lid IB | E104: 24 | F104: 1300 | G104: =F104*90% -> 1170 | H104: =F104*90%*98% -> 1146.6 | I104: =F104*88% -> 1144 | J104: =F104*88%*98% -> 1121.12
A105: 10 | B105: W/P | C105: HA12-10 | D105: Wokpan With Glass Lid IB | E105: 26 | F105: 1440 | G105: =F105*90% -> 1296 | H105: =F105*90%*98% -> 1270.08 | I105: =F105*88% -> 1267.2 | J105: =F105*88%*98% -> 1241.856
A106: 11 | B106: W/P | C106: HA12-11 | D106: Wokpan With Glass Lid IB | E106: 28 | F106: 1575 | G106: =F106*90% -> 1417.5 | H106: =F106*90%*98% -> 1389.15 | I106: =F106*88% -> 1386 | J106: =F106*88%*98% -> 1358.28
A107: 12 | B107: W/P | C107: HA12-12 | D107: Wokpan With Glass Lid IB | E107: 30 | F107: 1710 | G107: =F107*90% -> 1539 | H107: =F107*90%*98% -> 1508.22 | I107: =F107*88% -> 1504.8 | J107: =F107*88%*98% -> 1474.704
A110: SL | B110: Group | C110: Code | D110: Gift Set | E110: Size | F110: DP | G110: D. 10 | H110: B. 12 | I110: D. 12 | J110: B. 14
A111: 1 | B111: Gift | C111: HAG15-01 | D111: NS Gift Set- 7pcs | F111: 3780 | G111: =F111*90% -> 3402 | H111: =F111*90%*98% -> 3333.96 | I111: =F111*88% -> 3326.4 | J111: =F111*88%*98% -> 3259.872
A112: 2 | B112: Gift | C112: HAG15-02 | D112: NS Gift Set- 7pcs IB | F112: 4025 | G112: =F112*90% -> 3622.5 | H112: =F112*90%*98% -> 3550.05 | I112: =F112*88% -> 3542 | J112: =F112*88%*98% -> 3471.16
A115: SL | B115: Group | C115: Code | D115: Milk Pan | E115: Size | F115: DP | G115: D. 10 | H115: B. 12 | I115: D. 12 | J115: B. 14
A116: 1 | B116: M/P | C116: HA13-01 | D116: Milk Pan | E116: 18 | F116: 845 | G116: =F116*90% -> 760.5 | H116: =F116*90%*98% -> 745.29 | I116: =F116*88% -> 743.6 | J116: =F116*88%*98% -> 728.728
A117: 2 | B117: M/P | C117: HA13-02 | D117: Milk Pan IB | E117: 18 | F117: 915 | G117: =F117*90% -> 823.5 | H117: =F117*90%*98% -> 807.03 | I117: =F117*88% -> 805.2 | J117: =F117*88%*98% -> 789.096
A120: SL | B120: Group | C120: Code | D120: Milk Pan | E120: Size | F120: DP | G120: D. 6 | H120: B. 8
A121: 1 | B121: M/P | C121: HS7-01 | D121: SS Milk Pan | E121: 20 | F121: 1105 | G121: =F121*94% -> 1038.7 | H121: =F121*94%*98% -> 1017.926
A127: SL | B127: Group | C127: Code | D127: Ruti/Pizza Pan | E127: Size | F127: DP | G127: D. 10 | H127: B. 12 | I127: D. 12 | J127: B. 14
A128: 1 | B128: R/T | C128: HA7-01 | D128: Ruti Tawa | E128: 26 | F128: 845 | G128: =F128*90% -> 760.5 | H128: =F128*90%*98% -> 745.29 | I128: =F128*88% -> 743.6 | J128: =F128*88%*98% -> 728.728
A129: 2 | B129: R/T | C129: HA7-02 | D129: Ruti Tawa | E129: 28 | F129: 915 | G129: =F129*90% -> 823.5 | H129: =F129*90%*98% -> 807.03 | I129: =F129*88% -> 805.2 | J129: =F129*88%*98% -> 789.096
A130: 3 | B130: P/P | C130: HA8-01 | D130: Pizza Pan | E130: 24 | F130: 780 | G130: =F130*90% -> 702 | H130: =F130*90%*98% -> 687.96 | I130: =F130*88% -> 686.4 | J130: =F130*88%*98% -> 672.672
A131: 4 | B131: P/P | C131: HA8-02 | D131: Pizza Pan | E131: 26 | F131: 915 | G131: =F131*90% -> 823.5 | H131: =F131*90%*98% -> 807.03 | I131: =F131*88% -> 805.2 | J131: =F131*88%*98% -> 789.096
A132: 5 | B132: P/P | C132: HA8-03 | D132: Pizza Pan | E132: 28 | F132: 980 | G132: =F132*90% -> 882 | H132: =F132*90%*98% -> 864.36 | I132: =F132*88% -> 862.4 | J132: =F132*88%*98% -> 845.152
A133: 6 | B133: P/P | C133: HA8-04 | D133: Pizza Pan IB | E133: 24 | F133: 845 | G133: =F133*90% -> 760.5 | H133: =F133*90%*98% -> 745.29 | I133: =F133*88% -> 743.6 | J133: =F133*88%*98% -> 728.728
A134: 7 | B134: P/P | C134: HA8-05 | D134: Pizza Pan IB | E134: 26 | F134: 980 | G134: =F134*90% -> 882 | H134: =F134*90%*98% -> 864.36 | I134: =F134*88% -> 862.4 | J134: =F134*88%*98% -> 845.152
A135: 8 | B135: P/P | C135: HA8-06 | D135: Pizza Pan IB | E135: 28 | F135: 1040 | G135: =F135*90% -> 936 | H135: =F135*90%*98% -> 917.28 | I135: =F135*88% -> 915.2 | J135: =F135*88%*98% -> 896.896
A138: SL | B138: Group | C138: Code | D138: SS Sauce Pan | E138: Size | F138: DP | G138: D. 6 | H138: B. 8 | I138: D. 12 | J138: B. 14
A139: 1 | B139: S/P | C139: HS1-01 | D139: SS Sauce Pan Oval IB | E139: 20 | F139: 1080 | G139: =F139*94% -> 1015.2 | H139: =F139*94%*98% -> 994.896
A140: 2 | B140: S/P | C140: HS1-02 | D140: SS Sauce Pan Oval IB | E140: 22 | F140: 1210 | G140: =F140*94% -> 1137.4 | H140: =F140*94%*98% -> 1114.652
A141: 3 | B141: S/P | C141: HS1-03 | D141: SS Sauce Pan Oval IB | E141: 24 | F141: 1485 | G141: =F141*94% -> 1395.9 | H141: =F141*94%*98% -> 1367.982
...

Sheet Sheet4

Sheet Sheet3
C2: Group | E2: =Sheet1!G1 -> D. 10
C3: R/C | E3: B. 12
C4: P/C | E4: =Sheet1!I1 -> D. 12
C5: C/P | E5: =Sheet1!J1 -> B. 14
C6: F/P | E6: =Sheet1!G120 -> D. 6
C7: SS/F/P | E7: =Sheet1!H120 -> B. 8
C8: Gift
C9: W/P
C10: M/P
C11: R/T
C12: P/P
C13: S/P
C14: TH/P
C15: Plate
C16: Bowl
C17: K/Y
C18: I/C
C19: B/L
C20: G/S
